radiant/__init__.py
radiant/server.py
radiant/static/brython-3.9.1/README.txt
radiant/static/brython-3.9.1/brython.js
radiant/static/brython-3.9.1/brython_stdlib.js
radiant/static/brython-3.9.1/demo.html
radiant/static/brython-3.9.1/index.html
radiant/static/brython-3.9.1/load_brython.js
radiant/static/brython-3.9.1/unicode.txt
radiant/static/brython-3.9.5/README.txt
radiant/static/brython-3.9.5/brython.js
radiant/static/brython-3.9.5/brython_stdlib.js
radiant/static/brython-3.9.5/demo.html
radiant/static/brython-3.9.5/index.html
radiant/static/brython-3.9.5/load_brython.js
radiant/static/brython-3.9.5/unicode.txt
radiant/static/fonts/fontawesome-free-5.5.0-web/LICENSE.txt
radiant/static/fonts/fontawesome-free-5.5.0-web/css/all.css
radiant/static/fonts/fontawesome-free-5.5.0-web/css/all.min.css
radiant/static/fonts/fontawesome-free-5.5.0-web/css/brands.css
radiant/static/fonts/fontawesome-free-5.5.0-web/css/brands.min.css
radiant/static/fonts/fontawesome-free-5.5.0-web/css/fontawesome.css
radiant/static/fonts/fontawesome-free-5.5.0-web/css/fontawesome.min.css
radiant/static/fonts/fontawesome-free-5.5.0-web/css/regular.css
radiant/static/fonts/fontawesome-free-5.5.0-web/css/regular.min.css
radiant/static/fonts/fontawesome-free-5.5.0-web/css/solid.css
radiant/static/fonts/fontawesome-free-5.5.0-web/css/solid.min.css
radiant/static/fonts/fontawesome-free-5.5.0-web/css/svg-with-js.css
radiant/static/fonts/fontawesome-free-5.5.0-web/css/svg-with-js.min.css
radiant/static/fonts/fontawesome-free-5.5.0-web/css/v4-shims.css
radiant/static/fonts/fontawesome-free-5.5.0-web/css/v4-shims.min.css
radiant/static/fonts/fontawesome-free-5.5.0-web/webfonts/fa-brands-400.eot
radiant/static/fonts/fontawesome-free-5.5.0-web/webfonts/fa-brands-400.svg
radiant/static/fonts/fontawesome-free-5.5.0-web/webfonts/fa-brands-400.ttf
radiant/static/fonts/fontawesome-free-5.5.0-web/webfonts/fa-brands-400.woff
radiant/static/fonts/fontawesome-free-5.5.0-web/webfonts/fa-brands-400.woff2
radiant-3.3.2.dist-info/LICENSE
radiant-3.3.2.dist-info/METADATA
radiant-3.3.2.dist-info/WHEEL
radiant-3.3.2.dist-info/top_level.txt
radiant-3.3.2.dist-info/RECORD
